LICENSE
MANIFEST.in
README.md
setup.py
lida/__init__.py
lida/cli.py
lida/datamodel.py
lida/utils.py
lida/version.py
lida/components/__init__.py
lida/components/executor.py
lida/components/goal.py
lida/components/infographer.py
lida/components/manager.py
lida/components/scaffold.py
lida/components/summarizer.py
lida/components/viz/__init__.py
lida/components/viz/vizeditor.py
lida/components/viz/vizevaluator.py
lida/components/viz/vizexplainer.py
lida/components/viz/vizgenerator.py
lida/components/viz/vizrecommender.py
lida/components/viz/vizrepairer.py
lida/web/__init__.py
lida/web/app.py
lida/web/ui/21614df092a0a42959abd49fa5ffec5702fa9463-676cade37ced82f048bc.js
lida/web/ui/21614df092a0a42959abd49fa5ffec5702fa9463-676cade37ced82f048bc.js.map
lida/web/ui/404.html
lida/web/ui/81e257386408544e35976acc2a4075b730ed48a4-7b8f3173a2b44bbab6cd.js
lida/web/ui/81e257386408544e35976acc2a4075b730ed48a4-7b8f3173a2b44bbab6cd.js.LICENSE.txt
lida/web/ui/81e257386408544e35976acc2a4075b730ed48a4-7b8f3173a2b44bbab6cd.js.map
lida/web/ui/app-e2b657f0ab713648c7d3.js
lida/web/ui/app-e2b657f0ab713648c7d3.js.map
lida/web/ui/chunk-map.json
lida/web/ui/component---src-pages-404-tsx-271998ff555bf33bd7ce.js
lida/web/ui/component---src-pages-404-tsx-271998ff555bf33bd7ce.js.map
lida/web/ui/component---src-pages-demo-tsx-3627df90d65f4ae79124.js
lida/web/ui/component---src-pages-demo-tsx-3627df90d65f4ae79124.js.LICENSE.txt
lida/web/ui/component---src-pages-demo-tsx-3627df90d65f4ae79124.js.map
lida/web/ui/component---src-pages-index-tsx-afa4f57a88f8802e62c1.js
lida/web/ui/component---src-pages-index-tsx-afa4f57a88f8802e62c1.js.map
lida/web/ui/component---src-pages-login-tsx-bbe1cb64566ee588bf48.js
lida/web/ui/component---src-pages-login-tsx-bbe1cb64566ee588bf48.js.map
lida/web/ui/favicon-32x32.png
lida/web/ui/framework-adcf09f5896f386aa38b.js
lida/web/ui/framework-adcf09f5896f386aa38b.js.LICENSE.txt
lida/web/ui/framework-adcf09f5896f386aa38b.js.map
lida/web/ui/index.html
lida_zk.egg-info/PKG-INFO
lida_zk.egg-info/SOURCES.txt
lida_zk.egg-info/dependency_links.txt
lida_zk.egg-info/requires.txt
lida_zk.egg-info/top_level.txt